pasteuwsgi
