Metadata-Version: 1.0
Name: pasteuwsgi
Version: 0.1.7
Summary: Paster command to use uwsgi as server for local development
Home-page: http://pypi.python.org/pypi/pasteuwsgi/
Author: Giacomo Bagnoli
Author-email: g.bagnoli@asidev.com
License: This is the MIT license: http://www.opensource.org/licenses/mit-license.php
